Metadata-Version: 2.1
Name: kapediaml150
Version: 150.0.0
Summary: Simple ocr work
Home-page: 
Author: Tapendra Baduwal
Author-email: tapendrabaduwal200@gmail.com
Classifier: Programming Language :: Python :: 3
Classifier: License :: OSI Approved :: MIT License
Classifier: Operating System :: OS Independent
License-File: LICENSE
